Encryptus/__init__.py
Encryptus-1.0.0.dist-info/METADATA
Encryptus-1.0.0.dist-info/WHEEL
Encryptus-1.0.0.dist-info/top_level.txt
Encryptus-1.0.0.dist-info/RECORD
